LICENSE
MANIFEST.in
README.md
setup.cfg
setup.py
Laka.egg-info/PKG-INFO
Laka.egg-info/SOURCES.txt
Laka.egg-info/dependency_links.txt
Laka.egg-info/requires.txt
Laka.egg-info/top_level.txt
laka/__init__.py
laka/command.py
laka/consul.py
laka/errors.py
laka/fofo.py
laka/handler.py
laka/laka_client.py
laka/laka_server.py
laka/laka_service.py
laka/param.py
laka/response.py