Metadata-Version: 2.1
Name: Laka
Version: 0.3
Summary: Micro Service Framework for Python
Home-page: https://github.com/olivetree123/Laka
Author: olivetree
Author-email: olivetree123@163.com
License: MIT
Platform: UNKNOWN
Classifier: Development Status :: 4 - Beta
Classifier: Programming Language :: Python :: 2.7
Classifier: Programming Language :: Python :: 3.5
Classifier: Programming Language :: Python :: 3.6
Classifier: Programming Language :: Python :: 3.7
